odoo/addons/mail_environment/README.rst
odoo/addons/mail_environment/__init__.py
odoo/addons/mail_environment/__manifest__.py
odoo/addons/mail_environment/i18n/de.po
odoo/addons/mail_environment/i18n/en.po
odoo/addons/mail_environment/i18n/es.po
odoo/addons/mail_environment/i18n/hr.po
odoo/addons/mail_environment/i18n/pt_BR.po
odoo/addons/mail_environment/i18n/sl.po
odoo/addons/mail_environment/i18n/zh_CN.po
odoo/addons/mail_environment/models/__init__.py
odoo/addons/mail_environment/models/fetchmail_server.py
odoo/addons/mail_environment/models/ir_mail_server.py
odoo/addons/mail_environment/views/fetchmail_server_views.xml
odoo11_addon_mail_environment-11.0.1.0.0.dist-info/DESCRIPTION.rst
odoo11_addon_mail_environment-11.0.1.0.0.dist-info/METADATA
odoo11_addon_mail_environment-11.0.1.0.0.dist-info/RECORD
odoo11_addon_mail_environment-11.0.1.0.0.dist-info/WHEEL
odoo11_addon_mail_environment-11.0.1.0.0.dist-info/metadata.json
odoo11_addon_mail_environment-11.0.1.0.0.dist-info/top_level.txt
